coar_notify_validator/__init__.py
coar_notify_validator/exceptions.py
coar_notify_validator/results_parser.py
coar_notify_validator/validate.py
coar_notify_validator/shape_files/__init__.py
coar_notify_validator/shape_files/types.py
coar_notify_validator/shape_files/utils.py
coar_notify_validator/shape_files/data/CoarActor.ttl
coar_notify_validator/shape_files/data/accept-review-shape.ttl
coar_notify_validator/shape_files/data/acknowledge-and-reject-shape.ttl
coar_notify_validator/shape_files/data/acknowledge-and-tentative-accept-shape.ttl
coar_notify_validator/shape_files/data/acknowledge-and-tentative-reject-shape.ttl
coar_notify_validator/shape_files/data/announce-endorse-shape.ttl
coar_notify_validator/shape_files/data/announce-ingest-shape.ttl
coar_notify_validator/shape_files/data/announce-relationship-shape.ttl
coar_notify_validator/shape_files/data/announce-review-shape.ttl
coar_notify_validator/shape_files/data/announce-shape.ttl
coar_notify_validator/shape_files/data/offer-endorse-shape.ttl
coar_notify_validator/shape_files/data/offer-ingest-shape.ttl
coar_notify_validator/shape_files/data/offer-review-shape.ttl
coar_notify_validator/shape_files/data/scen_2-1.shacl.ttl
coar_notify_validator/shape_files/data/scen_7-1.shacl.ttl
coar_notify_validator/shape_files/data/test-announce-endorse-shape.ttl
coar_notify_validator/shape_files/data/undo-shape.ttl
coar_notify_validator-0.0.4.dist-info/LICENSE
coar_notify_validator-0.0.4.dist-info/METADATA
coar_notify_validator-0.0.4.dist-info/WHEEL
coar_notify_validator-0.0.4.dist-info/top_level.txt
coar_notify_validator-0.0.4.dist-info/RECORD
