Metadata-Version: 2.1
Name: coar-notify-validator
Version: 0.0.4
Summary: Utility for validating COAR Notify payloads.
Home-page: https://github.com/seanwiseman/coar-notify-validator.git
Maintainer: Sean Wiseman
Maintainer-email: seanwiseman2012@gmail.com
License: MIT
Classifier: Development Status :: 3 - Alpha
Classifier: Intended Audience :: Developers
Classifier: License :: OSI Approved :: MIT License
Classifier: Programming Language :: Python :: 3
License-File: LICENSE
Requires-Dist: kglab (==0.6.6)
Requires-Dist: rdflib (==6.3.2)
Requires-Dist: pyshacl (==0.23.0)
